[
  {
    "title": "Money",
    "author": "Anitek",
    "audio": "https://f004.backblazeb2.com/file/qewavetunes/Money.mp3"
  },
  {
    "title": "Aria Math",
    "author": "C418",
    "audio": "https://f004.backblazeb2.com/file/qewavetunes/Aria+Math.mp3"
  },
  {
    "title": "retire",
    "author": "alvedon",
    "audio": "https://f004.backblazeb2.com/file/qewavetunes/alvedon+-+retire+(final)+4.mp3"
  },
  {
    "title": "Simppsonwave 1995",
    "author": "FrankJavCee",
    "audio": "https://f004.backblazeb2.com/file/qewavetunes/FrankJavCee+-+%EF%BC%B3%EF%BD%89%EF%BD%8D%EF%BD%90%EF%BD%93%EF%BD%8F%EF%BD%8E%EF%BD%97%EF%BD%81%EF%BD%96%EF%BD%85+%EF%BC%91%EF%BC%99%EF%BC%99%EF%BC%95+(Original+Music+Video)+4.mp3"
  },
  {
    "title": "Romance",
    "author": "Hiroshi Suzuki ",
    "audio": "https://f004.backblazeb2.com/file/qewavetunes/Hiroshi+Suzuki-Romance+4.mp3"
  },
  {
    "title": "Si o No",
    "author": "L'Eclair",
    "audio": "https://f004.backblazeb2.com/file/qewavetunes/Si+o+No.mp3"
  },
  {
    "title": "Street Market / Love Scene",
    "author": "Michael Small",
    "audio": "https://f004.backblazeb2.com/file/qewavetunes/Street+Market+_+Love+Scene+4.mp3"
  },
  {
    "title": "l8r h8r",
    "author": "Terekke",
    "audio": "https://f004.backblazeb2.com/file/qewavetunes/Terekke+-+l8r+h8r.mp3"
  },
  {
    "title": "snowfall",
    "author": "øneheart x reidenshi",
    "audio": "https://f004.backblazeb2.com/file/qewavetunes/%C3%B8neheart+x+reidenshi+-+snowfall+4.mp3"
  },
  {
    "title": "Can you hear the music",
    "author": "Ludwig Goransson",
    "audio": "https://f004.backblazeb2.com/file/qewavetunes/Can+You+Hear+The+Music+4.mp3"
  },
  {
    "title": "Newborn Sun",
    "author": "Chon",
    "audio": "https://f004.backblazeb2.com/file/qewavetunes/CHON+-+Newborn+Sun.mp3"
  },
  {
    "title": "Continue",
    "author": "Chon",
    "audio": "https://f004.backblazeb2.com/file/qewavetunes/Continue_.mp3"
  },
  {
    "title": "Chicago",
    "author": "Cookin Soul",
    "audio": "https://f004.backblazeb2.com/file/qewavetunes/Cookin+Soul+-+Chicago.mp3"
  },
  {
    "title": "Resonance",
    "author": "Home",
    "audio": "https://f004.backblazeb2.com/file/qewavetunes/HOME+-+Resonance+4.mp3"
  },
  {
    "title": "Love Theme From Spartacus (Rudy Van Gelder Remaster / 2006)",
    "author": "Yusef Lateef",
    "audio": "https://f004.backblazeb2.com/file/qewavetunes/Love+Theme+From+Spartacus+(Rudy+Van+Gelder+Remaster+_+2006).mp3"
  },
  {
    "title": "Numb",
    "author": "Men I Trust",
    "audio": "https://f004.backblazeb2.com/file/qewavetunes/Men+I+Trust+-+Numb+4.mp3"
  },
  {
    "title": "Sleep Walk",
    "author": "Deftones",
    "audio": "https://f004.backblazeb2.com/file/qewavetunes/Deftones+-+Sleepwalk+%5BHD%5D+4.mp3"
  },
  {
    "title": "Special K",
    "author": "Mac DeMarco",
    "audio": "https://f004.backblazeb2.com/file/qewavetunes/Special+K+4.mp3"
  },
  {
    "title": "Blade Runner 2049",
    "author": "Synthwave goose",
    "audio": "https://f004.backblazeb2.com/file/qewavetunes/Synthwave+goose+-+Blade+Runner+2049+4.mp3"
  },
  {
    "title": "The Thief in Marrakesh",
    "author": "Arc De Soleil",
    "audio": "https://f004.backblazeb2.com/file/qewavetunes/The+Thief+in+Marrakesh.mp3"
  },
  {
    "title": "Allude",
    "author": "Voyage",
    "audio": "https://f004.backblazeb2.com/file/qewavetunes/Voyage+-+Allude+4.mp3"
  },
  {
    "title": "Warmpop",
    "author": "ESPRIT 空想, George Clanton",
    "audio": "https://f004.backblazeb2.com/file/qewavetunes/ESPRIT+%E7%A9%BA%E6%83%B3%2C+George+Clanton+-+Warmpop.mp3"
  },
  {
    "title": "Flamboyan - Samba Lenta",
    "author": "Angel Pocho Gatti y su Orquesta",
    "audio": "https://f004.backblazeb2.com/file/qewavetunes/Flamboyan+(Samba+Lenta).mp3"
  },
  {
    "title": "Last summer in Rio",
    "author": "Azymuth",
    "audio": "https://f004.backblazeb2.com/file/qewavetunes/Azymuth+-+Last+Summer+In+Rio.mp3"
  },
  {
    "title": "1992 (Slowed + Reverb Extended Mix)",
    "author": "No_4m4t",
    "audio": "https://f004.backblazeb2.com/file/qewavetunes/1992+(Slowed+%2B+Reverb+Extended+Mix).mp3"
  },
  {
    "title": "BIOS",
    "author": "Zorrovian",
    "audio": "https://f004.backblazeb2.com/file/qewavetunes/BIOS+-+Zorrovian+%5BOfficial+Visualiser%5D.mp3"
  },  
  {
    "title": "とおくを つなぐもの",
    "author": "百景",
    "audio": "https://f004.backblazeb2.com/file/qewavetunes/Hyakkei+%E7%99%BE%E6%99%AF+-+%E3%81%A8%E3%81%8A%E3%81%8F%E3%82%92+%E3%81%A4%E3%81%AA%E3%81%90%E3%82%82%E3%81%AE+(Toku+Wo+Tsunagu+Mono)+full+album.mp3"
  },
  {
    "title": "We're Finally Landing",
    "author": "Home",
    "audio": "https://f004.backblazeb2.com/file/qewavetunes/We're+Finally+Landing.mp3"
  },
  {
    "title": "Ascend",
    "author": "oDDing",
    "audio": "https://f004.backblazeb2.com/file/qewavetunes/oDDling+-+Ascend.mp3"
  },
  {
    "title": "Idea 22",
    "author": "Gibran Alcocer",
    "audio": "https://f004.backblazeb2.com/file/qewavetunes/Idea+22.mp3"
  },
  {
    "title": "Idea 10",
    "author": "Gibran Alcocer ",
    "audio": "https://f004.backblazeb2.com/file/qewavetunes/Gibran+Alcocer+-+Idea+10.mp3"
  },
  {
    "title": "Idea 15 (Slowed + Reverb)",
    "author": "Gibran Alcocer ",
    "audio": "https://f004.backblazeb2.com/file/qewavetunes/Gibran+Alcocer+-+Idea+15+(Slowed+%2B+Reverb).mp3"
  },
  {
    "title": "There's something wrong with me",
    "author": "Son Lux",
    "audio": "https://f004.backblazeb2.com/file/qewavetunes/Son+Lux+-+There's+Something+Wrong+with+Me+(From+_Thunderbolts__Visualizer+Video).mp3"
  },
  {
    "title": "Not Alone",
    "author": "Son Lux",
    "audio": "https://f004.backblazeb2.com/file/qewavetunes/Son+Lux+-+Not+Alone+(From+_Thunderbolts__Visualizer+Video).mp3"
  },
  {
    "title": "It's Bucky!",
    "author": "Son Lux",
    "audio": "https://f004.backblazeb2.com/file/qewavetunes/Son+Lux+-+It's+Bucky!+(From+_Thunderbolts__Visualizer+Video).mp3"
  },
  {
    "title": "Flute Concerto in D Minor, Wq. 22: I. Allegro",
    "author": "Emmanuel Pahud, Trevor Pinnock, Kammerakademie Potsdam",
    "audio": "https://f004.backblazeb2.com/file/qewavetunes/Flute+Concerto+in+D+Minor_+I.+Allegro+(After+Harpsichord+Concerto%2C+Wq.+22).mp3"
  },
  {
    "title": "Vivaldi Variation (Arr. for Piano from Concerto for Strings in G Minor, RV 156",
    "author": "Florian Christl",
    "audio": "https://f004.backblazeb2.com/file/qewavetunes/Vivaldi+Variation+(Arr.+for+Piano+from+Concerto+for+Strings+in+G+Minor%2C+RV+156+by+F.+Christl).mp3"
  },
  {
    "title": "Chevalier Bulltoe ",
    "author": "TOTORRO",
    "audio": "https://f004.backblazeb2.com/file/qewavetunes/TOTORRO+-+Chevalier+Bulltoe+(audio).mp3"
  },
  {
    "title": "falkor",
    "author": "Covet",
    "audio": "https://f004.backblazeb2.com/file/qewavetunes/Covet+-+falkor+(Official+Audio).mp3"
  },
  {
    "title": "Everlong[instrumental]",
    "author": "Foo Fighters",
    "audio": "https://f004.backblazeb2.com/file/qewavetunes/Foo+Fighters+-+Everlong+(Official+Instrumental).mp3"
  },
  {
    "title": "My Own Summer (Shove It) [Instrumental]",
    "author": "Deftones",
    "audio": "https://f004.backblazeb2.com/file/qewavetunes/My+Own+Summer+(Shove+It)+%5BInstrumental%5D+HD.mp3"
  },
  {
    "title": "Be Quiet and Drive (Far Away)[instrumental]",
    "author": "Deftones",
    "audio": "https://f004.backblazeb2.com/file/qewavetunes/Deftones+-+Be+Quiet+and+Drive+(Far+Away)+-+Karaoke+Instrumental+Lyrics+-+ObsKure.mp3"
  },
  {
    "title": "Youngest Daughter [instrumental]",
    "author": "Superheaven",
    "audio": "https://f004.backblazeb2.com/file/qewavetunes/Superheaven+-+Youngest+Daughter+(Karaoke_Instrumental).mp3"
  },
  {
    "title": "When Something Is Gone",
    "author": "Punish or Pardon",
    "audio": "https://f004.backblazeb2.com/file/qewavetunes/When+Something+Is+Gone.mp3"
  },
  {
    "title": "Toxicity [Instrumental] ",
    "author": "System Of A Down",
    "audio": "https://f004.backblazeb2.com/file/qewavetunes/Toxicity+%5BInstrumental%5D+HD.mp3"
  },
  {
    "title": "Aerials [instrumental]",
    "author": "System Of A Down",
    "audio": "https://f004.backblazeb2.com/file/qewavetunes/System+of+a+Down+-+Aerials+(Instrumental).mp3"
  },
  {
    "title": "B.Y.O.B [instrumental]",
    "author": "System Of A Down",
    "audio": "https://f004.backblazeb2.com/file/qewavetunes/System+Of+A+Down+-+B.Y.O.B.+(Instrumental)+(High+Quality).mp3"
  },
  {
    "title": "Radio/Video[instrumental]",
    "author": "System Of A Down",
    "audio": "https://f004.backblazeb2.com/file/qewavetunes/System+Of+A+Down+-+Radio_Video+(Official+Instrumental)+HQ_.mp3"
  },
  {
    "title": " Money For Nothing (instrumental)",
    "author": "Dire Straits",
    "audio": "https://f004.backblazeb2.com/file/qewavetunes/Dire+Straits+-+Money+For+Nothing+(instrumental).mp3"
  }
]
